<?xml version="1.0" encoding="utf-8"?>
<odoo>
    <data>
        <!-- is.prodstar.fp2art -->
        <record id="is_prodstar_fp2art_tree_view" model="ir.ui.view">
            <field name="name">is.prodstar.fp2art.tree</field>
            <field name="model">is.prodstar.fp2art</field>
            <field name="arch" type="xml">
                <tree string="Prodstar FP2ART" default_order="code_pg">
                    <field name="soc"            optional="show"/>
                    <field name="code_pg"        optional="show"/>
                    <field name="designation"    optional="show"/>
                    <field name="cat"            optional="show"/>
                    <field name="fam"            optional="show"/>
                    <field name="gest"           optional="show"/>
                    <field name="moule"          optional="show"/>
                    <field name="projet"         optional="show"/>
                    <field name="ref_plan"       optional="hide"/>
                    <field name="ind"            optional="hide"/>
                    <field name="us"             optional="show"/>
                    <field name="uc"             optional="show"/>
                    <field name="uc_us"          optional="hide"/>
                    <field name="designation_uc" optional="hide"/>
                    <field name="um_uc"          optional="hide"/>
                    <field name="sr"             optional="hide"/>
                </tree>
            </field>
        </record>
        <record id="is_prodstar_fp2art_form_view" model="ir.ui.view">
            <field name="name">is.prodstar.fp2art.form</field>
            <field name="model">is.prodstar.fp2art</field>
            <field name="arch" type="xml">
                <form string="Prodstar FP2ART">
                    <sheet>
                        <group>
                            <group string="Informations générales">
                                <field name="soc"/>
                                <field name="code_pg"/>
                                <field name="designation"/>
                                <field name="cat"/>
                                <field name="fam"/>
                                <field name="gest"/>
                                <field name="moule"/>
                                <field name="projet"/>
                            </group>
                            <group string="Spécifications techniques">
                                <field name="ref_plan"/>
                                <field name="ind"/>
                                <field name="us"/>
                                <field name="uc"/>
                                <field name="uc_us"/>
                                <field name="designation_uc"/>
                                <field name="um_uc"/>
                                <field name="sr"/>
                            </group>
                        </group>
                        <group string="Spécifications internes">
                            <field name="specif_interne" nolabel="1"/>
                        </group>
                    </sheet>
                </form>
            </field>
        </record>
        <record id="is_prodstar_fp2art_search_view" model="ir.ui.view">
            <field name="name">is.prodstar.fp2art.search</field>
            <field name="model">is.prodstar.fp2art</field>
            <field name="arch" type="xml">
                <search>
                    <field name="code_pg" string="Code PG" filter_domain="[('code_pg','ilike',self)]"/>
                    <field name="designation" string="Désignation" filter_domain="[('designation','ilike',self)]"/>
                    <field name="moule" string="Moule" filter_domain="[('moule','ilike',self)]"/>
                    <field name="projet" string="Projet" filter_domain="[('projet','ilike',self)]"/>
                    <field name="gest" string="Gestionnaire" filter_domain="[('gest','ilike',self)]"/>
                    <group expand="0" string="Grouper par">
                        <filter name="group_soc" string="Société" context="{'group_by':'soc'}"/>
                        <filter name="group_cat" string="Catégorie" context="{'group_by':'cat'}"/>
                        <filter name="group_fam" string="Famille" context="{'group_by':'fam'}"/>
                        <filter name="group_gest" string="Gestionnaire" context="{'group_by':'gest'}"/>
                        <filter name="group_moule" string="Moule" context="{'group_by':'moule'}"/>
                        <filter name="group_projet" string="Projet" context="{'group_by':'projet'}"/>
                    </group>
                </search>
            </field>
        </record>
        <record id="is_prodstar_fp2art_action" model="ir.actions.act_window">
            <field name="name">Articles Prodstar</field>
            <field name="res_model">is.prodstar.fp2art</field>
            <field name="view_mode">tree,form</field>
        </record>

        <!-- is.prodstar.fp2nomq -->
        <record id="is_prodstar_fp2nomq_tree_view" model="ir.ui.view">
            <field name="name">is.prodstar.fp2nomq.tree</field>
            <field name="model">is.prodstar.fp2nomq</field>
            <field name="arch" type="xml">
                <tree string="Prodstar FP2NOMQ" default_order="compose, lig">
                    <field name="soc"         optional="show"/>
                    <field name="compose"     optional="show"/>
                    <field name="alternative" optional="show"/>
                    <field name="lig"         optional="show"/>
                    <field name="composant"   optional="show"/>
                    <field name="date_debut"  optional="show"/>
                    <field name="date_fin"    optional="show"/>
                    <field name="quantite"    optional="show"/>
                </tree>
            </field>
        </record>
        <record id="is_prodstar_fp2nomq_form_view" model="ir.ui.view">
            <field name="name">is.prodstar.fp2nomq.form</field>
            <field name="model">is.prodstar.fp2nomq</field>
            <field name="arch" type="xml">
                <form string="Prodstar FP2NOMQ">
                    <sheet>
                        <group>
                            <group string="Informations générales">
                                <field name="soc"/>
                                <field name="compose"/>
                                <field name="alternative"/>
                                <field name="lig"/>
                                <field name="composant"/>
                            </group>
                            <group string="Dates et quantité">
                                <field name="date_debut"/>
                                <field name="date_fin"/>
                                <field name="quantite"/>
                            </group>
                        </group>
                    </sheet>
                </form>
            </field>
        </record>
        <record id="is_prodstar_fp2nomq_search_view" model="ir.ui.view">
            <field name="name">is.prodstar.fp2nomq.search</field>
            <field name="model">is.prodstar.fp2nomq</field>
            <field name="arch" type="xml">
                <search>
                    <field name="compose" string="Composé" filter_domain="[('compose','ilike',self)]"/>
                    <field name="composant" string="Composant" filter_domain="[('composant','ilike',self)]"/>
                    <field name="alternative" string="Alternative" filter_domain="[('alternative','ilike',self)]"/>
                    
                    <group expand="0" string="Grouper par">
                        <filter name="group_soc" string="Société" context="{'group_by':'soc'}"/>
                        <filter name="group_compose" string="Composé" context="{'group_by':'compose'}"/>
                        <filter name="group_alternative" string="Alternative" context="{'group_by':'alternative'}"/>
                        <filter name="group_composant" string="Composant" context="{'group_by':'composant'}"/>
                    </group>
                </search>
            </field>
        </record>

        <record id="is_prodstar_fp2nomq_action" model="ir.actions.act_window">
            <field name="name">Nomenclatures Prodstar</field>
            <field name="res_model">is.prodstar.fp2nomq</field>
            <field name="view_mode">tree,form</field>
        </record>


        <!-- is.prodstar.fp2game -->
        <record id="is_prodstar_fp2game_tree_view" model="ir.ui.view">
            <field name="name">is.prodstar.fp2game.tree</field>
            <field name="model">is.prodstar.fp2game</field>
            <field name="arch" type="xml">
                <tree string="Prodstar FP2GAME" default_order="article, alternative">
                    <field name="soc"         optional="show"/>
                    <field name="article"     optional="show"/>
                    <field name="alternative" optional="show"/>
                    <field name="coef"        optional="show"/>
                </tree>
            </field>
        </record>
        <record id="is_prodstar_fp2game_form_view" model="ir.ui.view">
            <field name="name">is.prodstar.fp2game.form</field>
            <field name="model">is.prodstar.fp2game</field>
            <field name="arch" type="xml">
                <form string="Prodstar FP2GAME">
                    <sheet>
                        <group>
                            <field name="soc"/>
                            <field name="article"/>
                            <field name="alternative"/>
                            <field name="coef"/>
                        </group>
                    </sheet>
                </form>
            </field>
        </record>
        <record id="is_prodstar_fp2game_search_view" model="ir.ui.view">
            <field name="name">is.prodstar.fp2game.search</field>
            <field name="model">is.prodstar.fp2game</field>
            <field name="arch" type="xml">
                <search>
                    <field name="article" string="Article" filter_domain="[('article','ilike',self)]"/>
                    <field name="alternative" string="Alternative" filter_domain="[('alternative','ilike',self)]"/>
                    
                    <group expand="0" string="Grouper par">
                        <filter name="group_soc" string="Société" context="{'group_by':'soc'}"/>
                        <filter name="group_article" string="Article" context="{'group_by':'article'}"/>
                        <filter name="group_alternative" string="Alternative" context="{'group_by':'alternative'}"/>
                    </group>
                </search>
            </field>
        </record>
        <record id="is_prodstar_fp2game_action" model="ir.actions.act_window">
            <field name="name">Gammes-Entête</field>
            <field name="res_model">is.prodstar.fp2game</field>
            <field name="view_mode">tree,form</field>
        </record>

        <!-- is.prodstar.fp2gamo -->
        <record id="is_prodstar_fp2gamo_tree_view" model="ir.ui.view">
            <field name="name">is.prodstar.fp2gamo.tree</field>
            <field name="model">is.prodstar.fp2gamo</field>
            <field name="arch" type="xml">
                <tree string="Prodstar FP2GAMO" default_order="article, alternative, ordre">
                    <field name="soc"            optional="show"/>
                    <field name="article"        optional="show"/>
                    <field name="alternative"    optional="show"/>
                    <field name="ordre"          optional="show"/>
                    <field name="qi0028"         optional="show"/>
                    <field name="type_section"   optional="show"/>
                    <field name="section"        optional="show"/>
                    <field name="sous_section"   optional="show"/>
                    <field name="tps_preparation" optional="show"/>
                    <field name="tps_fab"        optional="show"/>
                </tree>
            </field>
        </record>
        <record id="is_prodstar_fp2gamo_form_view" model="ir.ui.view">
            <field name="name">is.prodstar.fp2gamo.form</field>
            <field name="model">is.prodstar.fp2gamo</field>
            <field name="arch" type="xml">
                <form string="Prodstar FP2GAMO">
                    <sheet>
                        <group>
                            <group string="Informations générales">
                                <field name="soc"/>
                                <field name="article"/>
                                <field name="alternative"/>
                                <field name="ordre"/>
                                <field name="qi0028"/>
                            </group>
                            <group string="Sections et temps">
                                <field name="type_section"/>
                                <field name="section"/>
                                <field name="sous_section"/>
                                <field name="tps_preparation"/>
                                <field name="tps_fab"/>
                            </group>
                        </group>
                    </sheet>
                </form>
            </field>
        </record>
        <record id="is_prodstar_fp2gamo_search_view" model="ir.ui.view">
            <field name="name">is.prodstar.fp2gamo.search</field>
            <field name="model">is.prodstar.fp2gamo</field>
            <field name="arch" type="xml">
                <search>
                    <field name="article" string="Article" filter_domain="[('article','ilike',self)]"/>
                    <field name="alternative" string="Alternative" filter_domain="[('alternative','ilike',self)]"/>
                    <field name="section" string="Section" filter_domain="[('section','ilike',self)]"/>
                    <field name="qi0028" string="QI0028" filter_domain="[('qi0028','ilike',self)]"/>
                    
                    <group expand="0" string="Grouper par">
                        <filter name="group_soc" string="Société" context="{'group_by':'soc'}"/>
                        <filter name="group_article" string="Article" context="{'group_by':'article'}"/>
                        <filter name="group_alternative" string="Alternative" context="{'group_by':'alternative'}"/>
                        <filter name="group_type_section" string="Type section" context="{'group_by':'type_section'}"/>
                        <filter name="group_section" string="Section" context="{'group_by':'section'}"/>
                    </group>
                </search>
            </field>
        </record>
        <record id="is_prodstar_fp2gamo_action" model="ir.actions.act_window">
            <field name="name">Gammes-Opératoires</field>
            <field name="res_model">is.prodstar.fp2gamo</field>
            <field name="view_mode">tree,form</field>
        </record>


        <!-- is.prodstar.fp2gams -->
        <record id="is_prodstar_fp2gams_tree_view" model="ir.ui.view">
            <field name="name">is.prodstar.fp2gams.tree</field>
            <field name="model">is.prodstar.fp2gams</field>
            <field name="arch" type="xml">
                <tree string="Prodstar FP2GAMS" default_order="article, alternative">
                    <field name="soc"           optional="show"/>
                    <field name="article"       optional="show"/>
                    <field name="alternative"   optional="show"/>
                    <field name="sous_traitant" optional="show"/>
                    <field name="cout_fixe"     optional="show"/>
                    <field name="cout_variable" optional="show"/>
                </tree>
            </field>
        </record>

        <record id="is_prodstar_fp2gams_form_view" model="ir.ui.view">
            <field name="name">is.prodstar.fp2gams.form</field>
            <field name="model">is.prodstar.fp2gams</field>
            <field name="arch" type="xml">
                <form string="Prodstar FP2GAMS">
                    <sheet>
                        <group>
                            <group string="Informations article">
                                <field name="soc"/>
                                <field name="article"/>
                                <field name="alternative"/>
                                <field name="sous_traitant"/>
                            </group>
                            <group string="Coûts">
                                <field name="cout_fixe"/>
                                <field name="cout_variable"/>
                            </group>
                        </group>
                    </sheet>
                </form>
            </field>
        </record>

        <record id="is_prodstar_fp2gams_search_view" model="ir.ui.view">
            <field name="name">is.prodstar.fp2gams.search</field>
            <field name="model">is.prodstar.fp2gams</field>
            <field name="arch" type="xml">
                <search>
                    <field name="article" string="Article" filter_domain="[('article','ilike',self)]"/>
                    <field name="alternative" string="Alternative" filter_domain="[('alternative','ilike',self)]"/>
                    <field name="sous_traitant" string="Sous-traitant" filter_domain="[('sous_traitant','ilike',self)]"/>
                    
                    <group expand="0" string="Grouper par">
                        <filter name="group_soc" string="Société" context="{'group_by':'soc'}"/>
                        <filter name="group_article" string="Article" context="{'group_by':'article'}"/>
                        <filter name="group_alternative" string="Alternative" context="{'group_by':'alternative'}"/>
                        <filter name="group_sous_traitant" string="Sous-traitant" context="{'group_by':'sous_traitant'}"/>
                    </group>
                </search>
            </field>
        </record>

        <record id="is_prodstar_fp2gams_action" model="ir.actions.act_window">
            <field name="name">Gammes-Sous-traitance</field>
            <field name="res_model">is.prodstar.fp2gams</field>
            <field name="view_mode">tree,form</field>
        </record>

        <!-- is.prodstar.fp2gamu -->
        <record id="is_prodstar_fp2gamu_tree_view" model="ir.ui.view">
            <field name="name">is.prodstar.fp2gamu.tree</field>
            <field name="model">is.prodstar.fp2gamu</field>
            <field name="arch" type="xml">
                <tree string="Prodstar FP2GAMU" default_order="article, alternative, ordre">
                    <field name="soc"             optional="show"/>
                    <field name="article"         optional="show"/>
                    <field name="alternative"     optional="show"/>
                    <field name="ordre"           optional="show"/>
                    <field name="moule"           optional="show"/>
                    <field name="nb_empreintes"   optional="show"/>
                    <field name="coefficient_cpi" optional="show"/>
                </tree>
            </field>
        </record>
        <record id="is_prodstar_fp2gamu_form_view" model="ir.ui.view">
            <field name="name">is.prodstar.fp2gamu.form</field>
            <field name="model">is.prodstar.fp2gamu</field>
            <field name="arch" type="xml">
                <form string="Prodstar FP2GAMU">
                    <sheet>
                        <group>
                            <group string="Informations article">
                                <field name="soc"/>
                                <field name="article"/>
                                <field name="alternative"/>
                                <field name="ordre"/>
                            </group>
                            <group string="Moule et empreintes">
                                <field name="moule"/>
                                <field name="nb_empreintes"/>
                                <field name="coefficient_cpi"/>
                            </group>
                        </group>
                    </sheet>
                </form>
            </field>
        </record>
        <record id="is_prodstar_fp2gamu_search_view" model="ir.ui.view">
            <field name="name">is.prodstar.fp2gamu.search</field>
            <field name="model">is.prodstar.fp2gamu</field>
            <field name="arch" type="xml">
                <search>
                    <field name="article" string="Article" filter_domain="[('article','ilike',self)]"/>
                    <field name="alternative" string="Alternative" filter_domain="[('alternative','ilike',self)]"/>
                    <field name="moule" string="Moule" filter_domain="[('moule','ilike',self)]"/>
                    
                    <group expand="0" string="Grouper par">
                        <filter name="group_soc" string="Société" context="{'group_by':'soc'}"/>
                        <filter name="group_article" string="Article" context="{'group_by':'article'}"/>
                        <filter name="group_alternative" string="Alternative" context="{'group_by':'alternative'}"/>
                        <filter name="group_moule" string="Moule" context="{'group_by':'moule'}"/>
                    </group>
                </search>
            </field>
        </record>
        <record id="is_prodstar_fp2gamu_action" model="ir.actions.act_window">
            <field name="name">Gammes-Moules</field>
            <field name="res_model">is.prodstar.fp2gamu</field>
            <field name="view_mode">tree,form</field>
        </record>



        <!-- is.prodstar.fp2sec -->
        <record id="is_prodstar_fp2sec_tree_view" model="ir.ui.view">
            <field name="name">is.prodstar.fp2sec.tree</field>
            <field name="model">is.prodstar.fp2sec</field>
            <field name="arch" type="xml">
                <tree string="Prodstar FP2SEC" default_order="type_section, section, sous_section">
                    <field name="soc"          optional="show"/>
                    <field name="type_section"/>
                    <field name="section"/>
                    <field name="sous_section"/>
                    <field name="nom_section"/>
                    <field name="cout_preparation"/>
                    <field name="cout_unitaire"/>
                </tree>
            </field>
        </record>
        <record id="is_prodstar_fp2sec_form_view" model="ir.ui.view">
            <field name="name">is.prodstar.fp2sec.form</field>
            <field name="model">is.prodstar.fp2sec</field>
            <field name="arch" type="xml">
                <form string="Prodstar FP2SEC">
                    <sheet>
                        <group>
                            <group string="Informations section">
                                <field name="soc"/>
                                <field name="type_section"/>
                                <field name="section"/>
                                <field name="sous_section"/>
                                <field name="nom_section"/>
                            </group>
                            <group string="Codes produits">
                                <field name="cout_preparation"/>
                                <field name="cout_unitaire"/>
                            </group>
                        </group>
                    </sheet>
                </form>
            </field>
        </record>
        <record id="is_prodstar_fp2sec_search_view" model="ir.ui.view">
            <field name="name">is.prodstar.fp2sec.search</field>
            <field name="model">is.prodstar.fp2sec</field>
            <field name="arch" type="xml">
                <search>
                    <field name="nom_section" string="Nom section" filter_domain="[('nom_section','ilike',self)]"/>
                    <field name="section" string="Section" filter_domain="[('section','ilike',self)]"/>
                    <field name="sous_section" string="Sous-section" filter_domain="[('sous_section','ilike',self)]"/>
                    <field name="type_section" string="Type section" filter_domain="[('type_section','ilike',self)]"/>
                    
                    <group expand="0" string="Grouper par">
                        <filter name="group_soc" string="Société" context="{'group_by':'soc'}"/>
                        <filter name="group_type_section" string="Type section" context="{'group_by':'type_section'}"/>
                        <filter name="group_section" string="Section" context="{'group_by':'section'}"/>
                        <filter name="group_sous_section" string="Sous-section" context="{'group_by':'sous_section'}"/>
                    </group>
                </search>
            </field>
        </record>
        <record id="is_prodstar_fp2sec_action" model="ir.actions.act_window">
            <field name="name">Sections</field>
            <field name="res_model">is.prodstar.fp2sec</field>
            <field name="view_mode">tree,form</field>
        </record>

        <!-- is.prodstar.fa2rcp -->
        <record id="is_prodstar_fa2rcp_tree_view" model="ir.ui.view">
            <field name="name">is.prodstar.fa2rcp.tree</field>
            <field name="model">is.prodstar.fa2rcp</field>
            <field name="arch" type="xml">
                <tree string="Prodstar FA2RCP" default_order="date_rcp desc, num_rcp desc">
                    <field name="soc"           optional="show"/>
                    <field name="date_rcp"      optional="show"/>
                    <field name="num_rcp"       optional="show"/>
                    <field name="fournisseur"   optional="show"/>
                    <field name="code_fou"      optional="show"/>
                    <field name="code_pg"       optional="show"/>
                    <field name="num_cde"       optional="show"/>
                    <field name="lig"           optional="hide"/>
                    <field name="num_bl"        optional="show"/>
                    <field name="num_lot_fourn" optional="show"/>
                    <field name="us"            optional="show"/>
                    <field name="qt_rcp"        optional="show"/>
                    <field name="qt_fac"        optional="show"/>
                    <field name="ope_rcp"       optional="show"/>
                </tree>
            </field>
        </record>

        <record id="is_prodstar_fa2rcp_form_view" model="ir.ui.view">
            <field name="name">is.prodstar.fa2rcp.form</field>
            <field name="model">is.prodstar.fa2rcp</field>
            <field name="arch" type="xml">
                <form string="Prodstar FA2RCP">
                    <sheet>
                        <group>
                            <group string="Informations réception">
                                <field name="soc"/>
                                <field name="date_rcp"/>
                                <field name="num_rcp"/>
                                <field name="fournisseur"/>
                                <field name="code_fou"/>
                                <field name="ope_rcp"/>
                            </group>
                            <group string="Article et commande">
                                <field name="code_pg"/>
                                <field name="num_cde"/>
                                <field name="lig"/>
                                <field name="num_bl"/>
                                <field name="num_lot_fourn"/>
                                <field name="us"/>
                            </group>
                        </group>
                        <group>
                            <group string="Quantités">
                                <field name="qt_rcp"/>
                                <field name="qt_fac"/>
                            </group>
                        </group>
                    </sheet>
                </form>
            </field>
        </record>

        <record id="is_prodstar_fa2rcp_search_view" model="ir.ui.view">
            <field name="name">is.prodstar.fa2rcp.search</field>
            <field name="model">is.prodstar.fa2rcp</field>
            <field name="arch" type="xml">
                <search>
                    <field name="num_rcp" string="N°Rcp" filter_domain="[('num_rcp','ilike',self)]"/>
                    <field name="fournisseur" string="Fournisseur" filter_domain="[('fournisseur','ilike',self)]"/>
                    <field name="code_pg" string="Code PG" filter_domain="[('code_pg','ilike',self)]"/>
                    <field name="num_bl" string="N°BL" filter_domain="[('num_bl','ilike',self)]"/>
                    <field name="num_cde" string="N°Cde" filter_domain="[('num_cde','ilike',self)]"/>
                    
                    <group expand="0" string="Grouper par">
                        <filter name="group_soc" string="Société" context="{'group_by':'soc'}"/>
                        <filter name="group_date_rcp" string="Date réception" context="{'group_by':'date_rcp'}"/>
                        <filter name="group_fournisseur" string="Fournisseur" context="{'group_by':'fournisseur'}"/>
                        <filter name="group_code_pg" string="Code PG" context="{'group_by':'code_pg'}"/>
                        <filter name="group_ope_rcp" string="Opérateur réception" context="{'group_by':'ope_rcp'}"/>
                    </group>
                </search>
            </field>
        </record>

        <record id="is_prodstar_fa2rcp_action" model="ir.actions.act_window">
            <field name="name">Réceptions</field>
            <field name="res_model">is.prodstar.fa2rcp</field>
            <field name="view_mode">tree,form</field>
        </record>

        <!-- is.prodstar.fa2fou -->
        <record id="is_prodstar_fa2fou_tree_view" model="ir.ui.view">
            <field name="name">is.prodstar.fa2fou.tree</field>
            <field name="model">is.prodstar.fa2fou</field>
            <field name="arch" type="xml">
                <tree string="Prodstar FA2FOU - Fournisseurs" default_order="code_fournisseur">
                    <field name="soc"              optional="show"/>
                    <field name="code_fournisseur" optional="show"/>
                    <field name="raison_sociale"   optional="show"/>
                    <field name="rue1"             optional="hide"/>
                    <field name="rue2"             optional="hide"/>
                    <field name="cp"               optional="show"/>
                    <field name="ville"            optional="show"/>
                    <field name="critere_alpha"    optional="hide"/>
                    <field name="categorie"        optional="show"/>
                    <field name="contact"          optional="show"/>
                    <field name="telephone"        optional="show"/>
                    <field name="fax"              optional="hide"/>
                </tree>
            </field>
        </record>

        <record id="is_prodstar_fa2fou_form_view" model="ir.ui.view">
            <field name="name">is.prodstar.fa2fou.form</field>
            <field name="model">is.prodstar.fa2fou</field>
            <field name="arch" type="xml">
                <form string="Prodstar FA2FOU - Fournisseurs">
                    <sheet>
                        <group>
                            <group string="Identification">
                                <field name="soc"/>
                                <field name="code_fournisseur"/>
                                <field name="raison_sociale"/>
                                <field name="critere_alpha"/>
                                <field name="categorie"/>
                            </group>
                            <group string="Coordonnées">
                                <field name="rue1"/>
                                <field name="rue2"/>
                                <field name="cp"/>
                                <field name="ville"/>
                                <field name="contact"/>
                                <field name="telephone"/>
                                <field name="fax"/>
                            </group>
                        </group>
                    </sheet>
                </form>
            </field>
        </record>

        <record id="is_prodstar_fa2fou_search_view" model="ir.ui.view">
            <field name="name">is.prodstar.fa2fou.search</field>
            <field name="model">is.prodstar.fa2fou</field>
            <field name="arch" type="xml">
                <search>
                    <field name="code_fournisseur" string="Code Fournisseur" filter_domain="[('code_fournisseur','ilike',self)]"/>
                    <field name="raison_sociale" string="Raison Sociale" filter_domain="[('raison_sociale','ilike',self)]"/>
                    <field name="ville" string="Ville" filter_domain="[('ville','ilike',self)]"/>
                    <field name="categorie" string="Catégorie" filter_domain="[('categorie','ilike',self)]"/>
                    
                    <group expand="0" string="Grouper par">
                        <filter name="group_soc" string="Société" context="{'group_by':'soc'}"/>
                        <filter name="group_categorie" string="Catégorie" context="{'group_by':'categorie'}"/>
                        <filter name="group_ville" string="Ville" context="{'group_by':'ville'}"/>
                    </group>
                </search>
            </field>
        </record>

        <record id="is_prodstar_fa2fou_action" model="ir.actions.act_window">
            <field name="name">Fournisseurs</field>
            <field name="res_model">is.prodstar.fa2fou</field>
            <field name="view_mode">tree,form</field>
        </record>

        <!-- is.prodstar.tarif_cial -->
        <record id="is_prodstar_tarif_cial_tree_view" model="ir.ui.view">
            <field name="name">is.prodstar.tarif_cial.tree</field>
            <field name="model">is.prodstar.tarif_cial</field>
            <field name="arch" type="xml">
                <tree string="Prodstar Tarif Commercial" default_order="client, code_pg, ind_prix">
                    <field name="client"        optional="show"/>
                    <field name="code_pg"       optional="show"/>
                    <field name="ind_prix"      optional="show"/>
                    <field name="moule"         optional="show"/>
                    <field name="plastika"      optional="hide"/>
                    <field name="date_debut"    optional="show"/>
                    <field name="date_fin"      optional="show"/>
                    <field name="type_evolu"    optional="hide"/>
                    <field name="projet"        optional="show"/>
                    <field name="part_mat"      optional="hide"/>
                    <field name="part_comp"     optional="hide"/>
                    <field name="part_emb"      optional="hide"/>
                    <field name="va_inj"        optional="hide"/>
                    <field name="va_ass"        optional="hide"/>
                    <field name="frais_port"    optional="hide"/>
                    <field name="logistique"    optional="hide"/>
                    <field name="amt_moule"     optional="hide"/>
                    <field name="cout_preserie" optional="hide"/>
                    <field name="prix_vente"    optional="show"/>
                </tree>
            </field>
        </record>

        <record id="is_prodstar_tarif_cial_form_view" model="ir.ui.view">
            <field name="name">is.prodstar.tarif_cial.form</field>
            <field name="model">is.prodstar.tarif_cial</field>
            <field name="arch" type="xml">
                <form string="Prodstar Tarif Commercial">
                    <sheet>
                        <group>
                            <group string="Identification">
                                <field name="client"/>
                                <field name="code_pg"/>
                                <field name="ind_prix"/>
                                <field name="moule"/>
                                <field name="plastika"/>
                                <field name="projet"/>
                            </group>
                            <group string="Dates et évolution">
                                <field name="date_debut"/>
                                <field name="date_fin"/>
                                <field name="type_evolu"/>
                                <field name="prix_vente"/>
                            </group>
                        </group>
                        <group>
                            <group string="Parts matières et composants">
                                <field name="part_mat"/>
                                <field name="part_comp"/>
                                <field name="part_emb"/>
                            </group>
                            <group string="Valeurs ajoutées">
                                <field name="va_inj"/>
                                <field name="va_ass"/>
                            </group>
                        </group>
                        <group>
                            <group string="Frais et logistique">
                                <field name="frais_port"/>
                                <field name="logistique"/>
                            </group>
                            <group string="Coûts moule et pré-série">
                                <field name="amt_moule"/>
                                <field name="cout_preserie"/>
                            </group>
                        </group>
                        <group string="Commentaire">
                            <field name="commentaire" nolabel="1"/>
                        </group>
                    </sheet>
                </form>
            </field>
        </record>

        <record id="is_prodstar_tarif_cial_search_view" model="ir.ui.view">
            <field name="name">is.prodstar.tarif_cial.search</field>
            <field name="model">is.prodstar.tarif_cial</field>
            <field name="arch" type="xml">
                <search>
                    <field name="client" string="Client" filter_domain="[('client','ilike',self)]"/>
                    <field name="code_pg" string="Code PG" filter_domain="[('code_pg','ilike',self)]"/>
                    <field name="moule" string="Moule" filter_domain="[('moule','ilike',self)]"/>
                    <field name="projet" string="Projet" filter_domain="[('projet','ilike',self)]"/>
                    
                    <separator/>
                    <filter name="filter_actif" string="Tarif actif" domain="[('date_debut','&lt;=',context_today()),('date_fin','&gt;=',context_today())]"/>
                    
                    <group expand="0" string="Grouper par">
                        <filter name="group_client" string="Client" context="{'group_by':'client'}"/>
                        <filter name="group_code_pg" string="Code PG" context="{'group_by':'code_pg'}"/>
                        <filter name="group_moule" string="Moule" context="{'group_by':'moule'}"/>
                        <filter name="group_projet" string="Projet" context="{'group_by':'projet'}"/>
                    </group>
                </search>
            </field>
        </record>

        <record id="is_prodstar_tarif_cial_action" model="ir.actions.act_window">
            <field name="name">Tarifs Commerciaux</field>
            <field name="res_model">is.prodstar.tarif_cial</field>
            <field name="view_mode">tree,form</field>
        </record>

        <!-- is.prodstar.fc2tad -->
        <record id="is_prodstar_fc2tad_tree_view" model="ir.ui.view">
            <field name="name">is.prodstar.fc2tad.tree</field>
            <field name="model">is.prodstar.fc2tad</field>
            <field name="arch" type="xml">
                <tree string="Prodstar FC2TAD - Tarif Valide" default_order="soc, client, code_pg">
                    <field name="soc"          optional="show"/>
                    <field name="client"       optional="show"/>
                    <field name="code_pg"      optional="show"/>
                    <field name="cat"          optional="show"/>
                    <field name="gest"         optional="show"/>
                    <field name="moule"        optional="show"/>
                    <field name="designation"  optional="show"/>
                    <field name="ref_client"   optional="show"/>
                    <field name="uc1"          optional="hide"/>
                    <field name="uc1_uv"       optional="hide"/>
                    <field name="uc2"          optional="hide"/>
                    <field name="uc2_uc1"      optional="hide"/>
                    <field name="date_bascule" optional="show"/>
                    <field name="date_debut"   optional="show"/>
                    <field name="prix"         optional="show"/>
                    <field name="dev"          optional="show"/>
                </tree>
            </field>
        </record>

        <record id="is_prodstar_fc2tad_form_view" model="ir.ui.view">
            <field name="name">is.prodstar.fc2tad.form</field>
            <field name="model">is.prodstar.fc2tad</field>
            <field name="arch" type="xml">
                <form string="Prodstar FC2TAD - Tarif Valide">
                    <sheet>
                        <group>
                            <group string="Identification">
                                <field name="soc"/>
                                <field name="client"/>
                                <field name="code_pg"/>
                                <field name="designation"/>
                                <field name="ref_client"/>
                            </group>
                            <group string="Classification">
                                <field name="cat"/>
                                <field name="gest"/>
                                <field name="moule"/>
                                <field name="dev"/>
                            </group>
                        </group>
                        <group>
                            <group string="Unités de conditionnement">
                                <field name="uc1"/>
                                <field name="uc1_uv"/>
                                <field name="uc2"/>
                                <field name="uc2_uc1"/>
                            </group>
                            <group string="Dates et prix">
                                <field name="date_bascule"/>
                                <field name="date_debut"/>
                                <field name="prix"/>
                            </group>
                        </group>
                    </sheet>
                </form>
            </field>
        </record>

        <record id="is_prodstar_fc2tad_search_view" model="ir.ui.view">
            <field name="name">is.prodstar.fc2tad.search</field>
            <field name="model">is.prodstar.fc2tad</field>
            <field name="arch" type="xml">
                <search>
                    <field name="client" string="Client" filter_domain="[('client','ilike',self)]"/>
                    <field name="code_pg" string="Code PG" filter_domain="[('code_pg','ilike',self)]"/>
                    <field name="moule" string="Moule" filter_domain="[('moule','ilike',self)]"/>
                    <field name="designation" string="Désignation" filter_domain="[('designation','ilike',self)]"/>
                    
                    <separator/>
                    <filter name="filter_actif" string="Tarif actif" domain="[('date_debut','&lt;=',context_today())]"/>
                    
                    <group expand="0" string="Grouper par">
                        <filter name="group_soc" string="Société" context="{'group_by':'soc'}"/>
                        <filter name="group_client" string="Client" context="{'group_by':'client'}"/>
                        <filter name="group_code_pg" string="Code PG" context="{'group_by':'code_pg'}"/>
                        <filter name="group_cat" string="Catégorie" context="{'group_by':'cat'}"/>
                        <filter name="group_gest" string="Gestionnaire" context="{'group_by':'gest'}"/>
                    </group>
                </search>
            </field>
        </record>

        <record id="is_prodstar_fc2tad_action" model="ir.actions.act_window">
            <field name="name">Tarifs Valides</field>
            <field name="res_model">is.prodstar.fc2tad</field>
            <field name="view_mode">tree,form</field>
        </record>

        <!-- is.prodstar.fc2lid -->
        <record id="is_prodstar_fc2lid_tree_view" model="ir.ui.view">
            <field name="name">is.prodstar.fc2lid.tree</field>
            <field name="model">is.prodstar.fc2lid</field>
            <field name="arch" type="xml">
                <tree string="Prodstar FC2LID - Livraisons" default_order="soc, num_liv, lig_liv">
                    <field name="soc"              optional="show"/>
                    <field name="client"           optional="show"/>
                    <field name="adr"              optional="hide"/>
                    <field name="code_pg"          optional="show"/>
                    <field name="cat"              optional="show"/>
                    <field name="fam"              optional="hide"/>
                    <field name="gest"             optional="show"/>
                    <field name="moule"            optional="show"/>
                    <field name="projet"           optional="show"/>
                    <field name="designation"      optional="show"/>
                    <field name="ref_client"       optional="show"/>
                    <field name="t"                optional="hide"/>
                    <field name="num_cde_prodstar" optional="show"/>
                    <field name="lig"              optional="hide"/>
                    <field name="num_cde_client"   optional="show"/>
                    <field name="num_liv"          optional="show"/>
                    <field name="lig_liv"          optional="show"/>
                    <field name="date_exp"         optional="show"/>
                    <field name="date_liv"         optional="show"/>
                    <field name="qt_liv_us"        optional="show"/>
                    <field name="qt_liv_uc"        optional="show"/>
                    <field name="montant"          optional="show"/>
                    <field name="date_confirme"    optional="hide"/>
                </tree>
            </field>
        </record>

        <record id="is_prodstar_fc2lid_form_view" model="ir.ui.view">
            <field name="name">is.prodstar.fc2lid.form</field>
            <field name="model">is.prodstar.fc2lid</field>
            <field name="arch" type="xml">
                <form string="Prodstar FC2LID - Livraisons">
                    <sheet>
                        <group>
                            <group string="Client et article">
                                <field name="soc"/>
                                <field name="client"/>
                                <field name="adr"/>
                                <field name="code_pg"/>
                                <field name="designation"/>
                                <field name="ref_client"/>
                            </group>
                            <group string="Classification">
                                <field name="cat"/>
                                <field name="fam"/>
                                <field name="gest"/>
                                <field name="moule"/>
                                <field name="projet"/>
                            </group>
                        </group>
                        <group>
                            <group string="Commande">
                                <field name="t"/>
                                <field name="num_cde_prodstar"/>
                                <field name="lig"/>
                                <field name="num_cde_client"/>
                            </group>
                            <group string="Livraison">
                                <field name="num_liv"/>
                                <field name="lig_liv"/>
                                <field name="date_exp"/>
                                <field name="date_liv"/>
                                <field name="date_confirme"/>
                            </group>
                        </group>
                        <group>
                            <group string="Quantités">
                                <field name="qt_liv_us"/>
                                <field name="qt_liv_uc"/>
                                <field name="montant"/>
                            </group>
                        </group>
                        <group string="Commentaire">
                            <field name="commentaire" nolabel="1"/>
                        </group>
                    </sheet>
                </form>
            </field>
        </record>

        <record id="is_prodstar_fc2lid_search_view" model="ir.ui.view">
            <field name="name">is.prodstar.fc2lid.search</field>
            <field name="model">is.prodstar.fc2lid</field>
            <field name="arch" type="xml">
                <search>
                    <field name="client" string="Client" filter_domain="[('client','ilike',self)]"/>
                    <field name="code_pg" string="Code PG" filter_domain="[('code_pg','ilike',self)]"/>
                    <field name="num_liv" string="N°Liv" filter_domain="[('num_liv','=',self)]"/>
                    <field name="num_cde_client" string="N°Cde Client" filter_domain="[('num_cde_client','ilike',self)]"/>
                    <field name="moule" string="Moule" filter_domain="[('moule','ilike',self)]"/>
                    <field name="projet" string="Projet" filter_domain="[('projet','ilike',self)]"/>
                    
                    <separator/>
                    <filter name="filter_exp_today" string="Expédition aujourd'hui" domain="[('date_exp','=',context_today())]"/>
                    <filter name="filter_exp_week" string="Expédition cette semaine" domain="[('date_exp','&gt;=',(context_today()-datetime.timedelta(days=7)).strftime('%Y-%m-%d'))]"/>
                    <filter name="filter_liv_today" string="Livraison aujourd'hui" domain="[('date_liv','=',context_today())]"/>
                    <filter name="filter_liv_week" string="Livraison cette semaine" domain="[('date_liv','&gt;=',(context_today()-datetime.timedelta(days=7)).strftime('%Y-%m-%d'))]"/>
                    
                    <group expand="0" string="Grouper par">
                        <filter name="group_soc" string="Société" context="{'group_by':'soc'}"/>
                        <filter name="group_client" string="Client" context="{'group_by':'client'}"/>
                        <filter name="group_code_pg" string="Code PG" context="{'group_by':'code_pg'}"/>
                        <filter name="group_cat" string="Catégorie" context="{'group_by':'cat'}"/>
                        <filter name="group_gest" string="Gestionnaire" context="{'group_by':'gest'}"/>
                        <filter name="group_moule" string="Moule" context="{'group_by':'moule'}"/>
                        <filter name="group_projet" string="Projet" context="{'group_by':'projet'}"/>
                        <filter name="group_date_exp" string="Date expédition" context="{'group_by':'date_exp'}"/>
                        <filter name="group_date_liv" string="Date livraison" context="{'group_by':'date_liv'}"/>
                    </group>
                </search>
            </field>
        </record>

        <record id="is_prodstar_fc2lid_action" model="ir.actions.act_window">
            <field name="name">Livraisons</field>
            <field name="res_model">is.prodstar.fc2lid</field>
            <field name="view_mode">tree,form</field>
        </record>


    </data>
</odoo>